{
  "data_root": "./data",
  "logging_root": "./runs",
  "train_test": "train",
  "exp_name": "test2",
  "checkpoint": null,
  "max_epoch": 100,
  "lr": 0.9e-4,
  "scheduler": "ReduceLROnPlateau",
  "batch_size": 1,
  "reg_weight": 0.0,
  "psf_file": "psfs/random_psf_50.npy",
  "K": 0.2,
  "learn_wiener": false,
  "resolution": 2496,
  "pixel_pitch": 6.4e-6,
  "focal_length": 5e-2,
  "r_cutoff": null,
  "refractive_idc": 1.4349,
  "wavelength": 530e-9,
  "target_side_length": 300,
  "init_fresnel": true,
  "single_image": true,
  "download_data": false
}